{"Explora\u00e7\u00e3o, Refino e Distribui\u00e7\u00e3o":{"P\/VP":2.15,"hoje":24.04,"inicio_ano":18.67,"inicio_mes":20.88,"inicio_seis_meses":18.38,"inicio_semana":23.45,"inicio_tres_meses":25.72,"percent_ano":28.76,"percent_hoje":2.52,"percent_mes":15.13,"percent_seis_meses":30.79,"percent_semana":2.52,"percent_tres_meses":-6.53},"Equipamentos e Servi\u00e7os":{"P\/VP":0.75,"hoje":7.18,"inicio_ano":2.67,"inicio_mes":6.53,"inicio_seis_meses":2.31,"inicio_semana":7.08,"inicio_tres_meses":3.4,"percent_ano":168.91,"percent_hoje":1.41,"percent_mes":9.95,"percent_seis_meses":210.82,"percent_semana":1.41,"percent_tres_meses":111.18},"Minerais Met\u00e1licos":{"P\/VP":1.52,"hoje":39.75,"inicio_ano":27.3,"inicio_mes":39.23,"inicio_seis_meses":24.33,"inicio_semana":40.04,"inicio_tres_meses":33.53,"percent_ano":45.6,"percent_hoje":-0.72,"percent_mes":1.33,"percent_seis_meses":63.38,"percent_semana":-0.72,"percent_tres_meses":18.55},"Siderurgia":{"P\/VP":1.68,"hoje":15.29,"inicio_ano":12.33,"inicio_mes":16.21,"inicio_seis_meses":9.34,"inicio_semana":15.72,"inicio_tres_meses":12.44,"percent_ano":24.01,"percent_hoje":-2.74,"percent_mes":-5.68,"percent_seis_meses":63.7,"percent_semana":-2.74,"percent_tres_meses":22.91},"Artefatos de Ferro e A\u00e7o":{"P\/VP":0.72,"hoje":15.31,"inicio_ano":9.68,"inicio_mes":15.36,"inicio_seis_meses":13.36,"inicio_semana":15.2,"inicio_tres_meses":17.04,"percent_ano":58.16,"percent_hoje":0.72,"percent_mes":-0.33,"percent_seis_meses":14.6,"percent_semana":0.72,"percent_tres_meses":-10.15},"Artefatos de Cobre":{"P\/VP":0.0,"hoje":10.2,"inicio_ano":23.97,"inicio_mes":9.62,"inicio_seis_meses":11.07,"inicio_semana":10.11,"inicio_tres_meses":12.25,"percent_ano":-57.45,"percent_hoje":0.89,"percent_mes":6.03,"percent_seis_meses":-7.86,"percent_semana":0.89,"percent_tres_meses":-16.73},"Petroqu\u00edmicos":{"P\/VP":0.61,"hoje":21.01,"inicio_ano":19.88,"inicio_mes":19.72,"inicio_seis_meses":15.22,"inicio_semana":20.89,"inicio_tres_meses":16.86,"percent_ano":5.68,"percent_hoje":0.57,"percent_mes":6.54,"percent_seis_meses":38.04,"percent_semana":0.57,"percent_tres_meses":24.61},"Fertilizantes e Defensivos":{"P\/VP":0.62,"hoje":2.66,"inicio_ano":17.33,"inicio_mes":115.92,"inicio_seis_meses":30.18,"inicio_semana":115.87,"inicio_tres_meses":45.48,"percent_ano":-84.65,"percent_hoje":-97.7,"percent_mes":-97.71,"percent_seis_meses":-91.19,"percent_semana":-97.7,"percent_tres_meses":-94.15},"Qu\u00edmicos Diversos":{"P\/VP":1.76,"hoje":35.78,"inicio_ano":29.51,"inicio_mes":31.25,"inicio_seis_meses":25.62,"inicio_semana":31.0,"inicio_tres_meses":27.68,"percent_ano":21.25,"percent_hoje":15.42,"percent_mes":14.5,"percent_seis_meses":39.66,"percent_semana":15.42,"percent_tres_meses":29.26},"Madeira":{"P\/VP":1.96,"hoje":21.59,"inicio_ano":10.81,"inicio_mes":21.1,"inicio_seis_meses":12.17,"inicio_semana":22.26,"inicio_tres_meses":20.13,"percent_ano":99.72,"percent_hoje":-3.01,"percent_mes":2.32,"percent_seis_meses":77.4,"percent_semana":-3.01,"percent_tres_meses":7.25},"Papel e Celulose":{"P\/VP":10.8,"hoje":19.05,"inicio_ano":23.53,"inicio_mes":27.52,"inicio_seis_meses":23.17,"inicio_semana":26.48,"inicio_tres_meses":24.6,"percent_ano":-19.04,"percent_hoje":-28.06,"percent_mes":-30.78,"percent_seis_meses":-17.78,"percent_semana":-28.06,"percent_tres_meses":-22.56},"Embalagens":{"P\/VP":0.29,"hoje":41.9,"inicio_ano":93.0,"inicio_mes":38.01,"inicio_seis_meses":50.0,"inicio_semana":41.9,"inicio_tres_meses":38.06,"percent_ano":-54.95,"percent_hoje":0.0,"percent_mes":10.23,"percent_seis_meses":-16.2,"percent_semana":0.0,"percent_tres_meses":10.09},"Materiais Diversos":{"P\/VP":0.0,"hoje":36.49,"inicio_ano":1.12,"inicio_mes":32.2,"inicio_seis_meses":1.12,"inicio_semana":32.2,"inicio_tres_meses":1.12,"percent_ano":3158.04,"percent_hoje":13.32,"percent_mes":13.32,"percent_seis_meses":3158.04,"percent_semana":13.32,"percent_tres_meses":3158.04},"Produtos para Constru\u00e7\u00e3o":{"P\/VP":3.72,"hoje":7.41,"inicio_ano":3.74,"inicio_mes":6.84,"inicio_seis_meses":2.99,"inicio_semana":7.55,"inicio_tres_meses":4.27,"percent_ano":98.13,"percent_hoje":-1.85,"percent_mes":8.33,"percent_seis_meses":147.83,"percent_semana":-1.85,"percent_tres_meses":73.54},"Constru\u00e7\u00e3o Pesada":{"P\/VP":0.0,"hoje":11.03,"inicio_ano":45.0,"inicio_mes":12.15,"inicio_seis_meses":3.78,"inicio_semana":11.0,"inicio_tres_meses":12.2,"percent_ano":-75.49,"percent_hoje":0.27,"percent_mes":-9.22,"percent_seis_meses":191.8,"percent_semana":0.27,"percent_tres_meses":-9.59},"Engenharia Consultiva":{"P\/VP":27.76,"hoje":22.68,"inicio_ano":8.8,"inicio_mes":21.75,"inicio_seis_meses":16.78,"inicio_semana":21.7,"inicio_tres_meses":19.08,"percent_ano":157.73,"percent_hoje":4.52,"percent_mes":4.28,"percent_seis_meses":35.16,"percent_semana":4.52,"percent_tres_meses":18.87},"Servi\u00e7os Diversos":{"P\/VP":6.52,"hoje":8.47,"inicio_ano":11.77,"inicio_mes":8.0,"inicio_seis_meses":7.17,"inicio_semana":8.42,"inicio_tres_meses":8.96,"percent_ano":-28.04,"percent_hoje":0.59,"percent_mes":5.88,"percent_seis_meses":18.13,"percent_semana":0.59,"percent_tres_meses":-5.47},"Material Aeron\u00e1utico e de Defesa":{"P\/VP":0.34,"hoje":7.32,"inicio_ano":21.54,"inicio_mes":6.03,"inicio_seis_meses":8.65,"inicio_semana":7.41,"inicio_tres_meses":7.66,"percent_ano":-66.02,"percent_hoje":-1.21,"percent_mes":21.39,"percent_seis_meses":-15.38,"percent_semana":-1.21,"percent_tres_meses":-4.44},"Material Rodovi\u00e1rio":{"P\/VP":3.38,"hoje":8.74,"inicio_ano":15.27,"inicio_mes":43.02,"inicio_seis_meses":20.21,"inicio_semana":43.24,"inicio_tres_meses":34.42,"percent_ano":-42.76,"percent_hoje":-79.79,"percent_mes":-79.68,"percent_seis_meses":-56.75,"percent_semana":-79.79,"percent_tres_meses":-74.61},"Motores, Compressores e Outros":{"P\/VP":7.67,"hoje":45.85,"inicio_ano":12.54,"inicio_mes":44.9,"inicio_seis_meses":24.12,"inicio_semana":47.36,"inicio_tres_meses":39.11,"percent_ano":265.63,"percent_hoje":-3.19,"percent_mes":2.12,"percent_seis_meses":90.09,"percent_semana":-3.19,"percent_tres_meses":17.23},"M\u00e1q. e Equip. Industriais":{"P\/VP":-4.46,"hoje":21.6,"inicio_ano":15.72,"inicio_mes":21.19,"inicio_seis_meses":16.78,"inicio_semana":21.51,"inicio_tres_meses":25.85,"percent_ano":37.4,"percent_hoje":0.42,"percent_mes":1.93,"percent_seis_meses":28.72,"percent_semana":0.42,"percent_tres_meses":-16.44},"M\u00e1q. e Equip. Constru\u00e7\u00e3o e Agr\u00edcolas":{"P\/VP":0.76,"hoje":28.08,"inicio_ano":15.05,"inicio_mes":26.5,"inicio_seis_meses":16.1,"inicio_semana":27.0,"inicio_tres_meses":22.4,"percent_ano":86.58,"percent_hoje":4.0,"percent_mes":5.96,"percent_seis_meses":74.41,"percent_semana":4.0,"percent_tres_meses":25.36},"Armas e Muni\u00e7\u00f5es":{"P\/VP":0.0,"hoje":7.87,"inicio_ano":7.21,"inicio_mes":7.33,"inicio_seis_meses":3.5,"inicio_semana":7.79,"inicio_tres_meses":5.1,"percent_ano":9.15,"percent_hoje":1.03,"percent_mes":7.37,"percent_seis_meses":124.86,"percent_semana":1.03,"percent_tres_meses":54.31},"Transporte A\u00e9reo":{"P\/VP":0.0,"hoje":25.54,"inicio_ano":30.89,"inicio_mes":19.05,"inicio_seis_meses":14.9,"inicio_semana":25.38,"inicio_tres_meses":18.86,"percent_ano":-17.32,"percent_hoje":0.63,"percent_mes":34.07,"percent_seis_meses":71.41,"percent_semana":0.63,"percent_tres_meses":35.42},"Transporte Ferrovi\u00e1rio":{"P\/VP":4.07,"hoje":19.03,"inicio_ano":15.06,"inicio_mes":17.35,"inicio_seis_meses":17.58,"inicio_semana":19.31,"inicio_tres_meses":21.06,"percent_ano":26.36,"percent_hoje":-1.45,"percent_mes":9.68,"percent_seis_meses":8.25,"percent_semana":-1.45,"percent_tres_meses":-9.64},"Transporte Hidrovi\u00e1rio":{"P\/VP":5.5,"hoje":37.96,"inicio_ano":13.07,"inicio_mes":37.5,"inicio_seis_meses":21.88,"inicio_semana":38.2,"inicio_tres_meses":30.22,"percent_ano":190.44,"percent_hoje":-0.63,"percent_mes":1.23,"percent_seis_meses":73.49,"percent_semana":-0.63,"percent_tres_meses":25.61},"Transporte Rodovi\u00e1rio":{"P\/VP":3.79,"hoje":25.12,"inicio_ano":17.74,"inicio_mes":21.12,"inicio_seis_meses":18.8,"inicio_semana":24.13,"inicio_tres_meses":27.81,"percent_ano":41.6,"percent_hoje":4.1,"percent_mes":18.94,"percent_seis_meses":33.62,"percent_semana":4.1,"percent_tres_meses":-9.67},"Explora\u00e7\u00e3o de Rodovias":{"P\/VP":5.27,"hoje":8.65,"inicio_ano":7.77,"inicio_mes":7.49,"inicio_seis_meses":7.94,"inicio_semana":8.53,"inicio_tres_meses":10.02,"percent_ano":11.33,"percent_hoje":1.41,"percent_mes":15.49,"percent_seis_meses":8.94,"percent_semana":1.41,"percent_tres_meses":-13.67},"Servi\u00e7os de Apoio e Armazenagem":{"P\/VP":2.78,"hoje":3.82,"inicio_ano":29.62,"inicio_mes":3.46,"inicio_seis_meses":3.23,"inicio_semana":3.75,"inicio_tres_meses":4.65,"percent_ano":-87.1,"percent_hoje":1.87,"percent_mes":10.4,"percent_seis_meses":18.27,"percent_semana":1.87,"percent_tres_meses":-17.85},"Material de Transporte":{"P\/VP":6.89,"hoje":12.01,"inicio_ano":4.28,"inicio_mes":13.2,"inicio_seis_meses":8.35,"inicio_semana":14.48,"inicio_tres_meses":12.7,"percent_ano":180.61,"percent_hoje":-17.06,"percent_mes":-9.02,"percent_seis_meses":43.83,"percent_semana":-17.06,"percent_tres_meses":-5.43},"Agricultura":{"P\/VP":1.06,"hoje":18.18,"inicio_ano":18.87,"inicio_mes":17.13,"inicio_seis_meses":15.03,"inicio_semana":17.91,"inicio_tres_meses":16.71,"percent_ano":-3.66,"percent_hoje":1.51,"percent_mes":6.13,"percent_seis_meses":20.96,"percent_semana":1.51,"percent_tres_meses":8.8},"A\u00e7ucar e Alcool":{"P\/VP":-0.87,"hoje":13.66,"inicio_ano":10.79,"inicio_mes":12.83,"inicio_seis_meses":10.95,"inicio_semana":13.52,"inicio_tres_meses":12.28,"percent_ano":26.6,"percent_hoje":1.04,"percent_mes":6.47,"percent_seis_meses":24.75,"percent_semana":1.04,"percent_tres_meses":11.24},"Carnes e Derivados":{"P\/VP":10.39,"hoje":26.07,"inicio_ano":11.05,"inicio_mes":24.76,"inicio_seis_meses":27.18,"inicio_semana":24.8,"inicio_tres_meses":28.07,"percent_ano":135.93,"percent_hoje":5.12,"percent_mes":5.29,"percent_seis_meses":-4.08,"percent_semana":5.12,"percent_tres_meses":-7.13},"Alimentos Diversos":{"P\/VP":2.05,"hoje":22.28,"inicio_ano":26.13,"inicio_mes":22.33,"inicio_seis_meses":20.08,"inicio_semana":22.99,"inicio_tres_meses":25.17,"percent_ano":-14.73,"percent_hoje":-3.09,"percent_mes":-0.22,"percent_seis_meses":10.96,"percent_semana":-3.09,"percent_tres_meses":-11.48},"Cervejas e Refrigerantes":{"P\/VP":2.76,"hoje":15.21,"inicio_ano":16.15,"inicio_mes":12.78,"inicio_seis_meses":11.34,"inicio_semana":14.22,"inicio_tres_meses":13.71,"percent_ano":-5.82,"percent_hoje":6.96,"percent_mes":19.01,"percent_seis_meses":34.13,"percent_semana":6.96,"percent_tres_meses":10.94},"Produtos de Uso Pessoal":{"P\/VP":2.68,"hoje":48.45,"inicio_ano":null,"inicio_mes":46.43,"inicio_seis_meses":35.52,"inicio_semana":49.37,"inicio_tres_meses":46.61,"percent_ano":null,"percent_hoje":-1.86,"percent_mes":4.35,"percent_seis_meses":36.4,"percent_semana":-1.86,"percent_tres_meses":3.95},"Produtos de Limpeza":{"P\/VP":0.0,"hoje":2.02,"inicio_ano":2.74,"inicio_mes":1.81,"inicio_seis_meses":1.72,"inicio_semana":1.93,"inicio_tres_meses":2.18,"percent_ano":-26.28,"percent_hoje":4.66,"percent_mes":11.6,"percent_seis_meses":17.44,"percent_semana":4.66,"percent_tres_meses":-7.34},"Alimentos":{"P\/VP":2.01,"hoje":43.36,"inicio_ano":51.98,"inicio_mes":40.47,"inicio_seis_meses":43.11,"inicio_semana":42.87,"inicio_tres_meses":45.4,"percent_ano":-16.58,"percent_hoje":1.14,"percent_mes":7.14,"percent_seis_meses":0.58,"percent_semana":1.14,"percent_tres_meses":-4.49},"Incorpora\u00e7\u00f5es":{"P\/VP":1.54,"hoje":13.4,"inicio_ano":8.65,"inicio_mes":11.21,"inicio_seis_meses":0.02,"inicio_semana":12.49,"inicio_tres_meses":13.95,"percent_ano":54.91,"percent_hoje":7.29,"percent_mes":19.54,"percent_seis_meses":66900.0,"percent_semana":7.29,"percent_tres_meses":-3.94},"Fios e Tecidos":{"P\/VP":0.76,"hoje":13.97,"inicio_ano":6.08,"inicio_mes":13.56,"inicio_seis_meses":7.22,"inicio_semana":13.64,"inicio_tres_meses":25.39,"percent_ano":129.77,"percent_hoje":2.42,"percent_mes":3.02,"percent_seis_meses":93.49,"percent_semana":2.42,"percent_tres_meses":-44.98},"Vestu\u00e1rio":{"P\/VP":1.9,"hoje":18.99,"inicio_ano":30.21,"inicio_mes":16.32,"inicio_seis_meses":14.96,"inicio_semana":18.96,"inicio_tres_meses":14.37,"percent_ano":-37.14,"percent_hoje":0.16,"percent_mes":16.36,"percent_seis_meses":26.94,"percent_semana":0.16,"percent_tres_meses":32.15},"Cal\u00e7ados":{"P\/VP":3.2,"hoje":14.03,"inicio_ano":9.69,"inicio_mes":13.67,"inicio_seis_meses":9.04,"inicio_semana":13.84,"inicio_tres_meses":11.14,"percent_ano":44.79,"percent_hoje":1.37,"percent_mes":2.63,"percent_seis_meses":55.2,"percent_semana":1.37,"percent_tres_meses":25.94},"Acess\u00f3rios":{"P\/VP":2.27,"hoje":16.16,"inicio_ano":14.81,"inicio_mes":14.31,"inicio_seis_meses":14.69,"inicio_semana":16.06,"inicio_tres_meses":15.88,"percent_ano":9.12,"percent_hoje":0.62,"percent_mes":12.93,"percent_seis_meses":10.01,"percent_semana":0.62,"percent_tres_meses":1.76},"Eletrodom\u00e9sticos":{"P\/VP":10.35,"hoje":16.72,"inicio_ano":4.8,"inicio_mes":16.32,"inicio_seis_meses":9.44,"inicio_semana":17.62,"inicio_tres_meses":16.05,"percent_ano":248.33,"percent_hoje":-5.11,"percent_mes":2.45,"percent_seis_meses":77.12,"percent_semana":-5.11,"percent_tres_meses":4.17},"Utens\u00edlios Dom\u00e9sticos":{"P\/VP":0.0,"hoje":7.79,"inicio_ano":6.82,"inicio_mes":7.4,"inicio_seis_meses":4.6,"inicio_semana":7.65,"inicio_tres_meses":8.0,"percent_ano":14.22,"percent_hoje":1.83,"percent_mes":5.27,"percent_seis_meses":69.35,"percent_semana":1.83,"percent_tres_meses":-2.62},"Autom\u00f3veis e Motocicletas":{"P\/VP":0.92,"hoje":12.48,"inicio_ano":19.75,"inicio_mes":12.24,"inicio_seis_meses":11.6,"inicio_semana":12.58,"inicio_tres_meses":11.71,"percent_ano":-36.81,"percent_hoje":-0.79,"percent_mes":1.96,"percent_seis_meses":7.59,"percent_semana":-0.79,"percent_tres_meses":6.58},"Hotelaria":{"P\/VP":0.0,"hoje":2.7,"inicio_ano":1.91,"inicio_mes":2.66,"inicio_seis_meses":1.96,"inicio_semana":2.68,"inicio_tres_meses":2.68,"percent_ano":41.36,"percent_hoje":0.75,"percent_mes":1.5,"percent_seis_meses":37.76,"percent_semana":0.75,"percent_tres_meses":0.75},"Restaurante e Similares":{"P\/VP":1.25,"hoje":7.51,"inicio_ano":13.8,"inicio_mes":6.22,"inicio_seis_meses":6.36,"inicio_semana":7.55,"inicio_tres_meses":7.19,"percent_ano":-45.58,"percent_hoje":-0.53,"percent_mes":20.74,"percent_seis_meses":18.08,"percent_semana":-0.53,"percent_tres_meses":4.45},"Bicicletas":{"P\/VP":0.52,"hoje":235.01,"inicio_ano":282.5,"inicio_mes":238.5,"inicio_seis_meses":187.0,"inicio_semana":242.0,"inicio_tres_meses":216.0,"percent_ano":-16.81,"percent_hoje":-2.89,"percent_mes":-1.46,"percent_seis_meses":25.67,"percent_semana":-2.89,"percent_tres_meses":8.8},"Brinquedos e Jogos":{"P\/VP":0.0,"hoje":25.5,"inicio_ano":12.5,"inicio_mes":25.0,"inicio_seis_meses":38.98,"inicio_semana":25.5,"inicio_tres_meses":29.3,"percent_ano":104.0,"percent_hoje":0.0,"percent_mes":2.0,"percent_seis_meses":-34.58,"percent_semana":0.0,"percent_tres_meses":-12.97},"Produ\u00e7\u00e3o de Eventos e Shows":{"P\/VP":4.96,"hoje":13.09,"inicio_ano":40.93,"inicio_mes":13.62,"inicio_seis_meses":12.44,"inicio_semana":13.9,"inicio_tres_meses":13.83,"percent_ano":-68.02,"percent_hoje":-5.83,"percent_mes":-3.89,"percent_seis_meses":5.23,"percent_semana":-5.83,"percent_tres_meses":-5.35},"Viagens e Turismo":{"P\/VP":3.58,"hoje":14.75,"inicio_ano":61.1,"inicio_mes":11.88,"inicio_seis_meses":13.8,"inicio_semana":14.69,"inicio_tres_meses":20.0,"percent_ano":-75.86,"percent_hoje":0.41,"percent_mes":24.16,"percent_seis_meses":6.88,"percent_semana":0.41,"percent_tres_meses":-26.25},"Servi\u00e7os Educacionais":{"P\/VP":1.97,"hoje":32.3,"inicio_ano":36.68,"inicio_mes":30.91,"inicio_seis_meses":29.13,"inicio_semana":31.96,"inicio_tres_meses":44.71,"percent_ano":-11.94,"percent_hoje":1.06,"percent_mes":4.5,"percent_seis_meses":10.88,"percent_semana":1.06,"percent_tres_meses":-27.76},"Aluguel de carros":{"P\/VP":3.88,"hoje":37.78,"inicio_ano":17.09,"inicio_mes":36.14,"inicio_seis_meses":19.42,"inicio_semana":37.69,"inicio_tres_meses":28.58,"percent_ano":121.06,"percent_hoje":0.24,"percent_mes":4.54,"percent_seis_meses":94.54,"percent_semana":0.24,"percent_tres_meses":32.19},"Programas de Fideliza\u00e7\u00e3o":{"P\/VP":1.37,"hoje":16.96,"inicio_ano":43.5,"inicio_mes":14.12,"inicio_seis_meses":14.28,"inicio_semana":16.59,"inicio_tres_meses":15.0,"percent_ano":-61.01,"percent_hoje":2.23,"percent_mes":20.11,"percent_seis_meses":18.77,"percent_semana":2.23,"percent_tres_meses":13.07},"Tecidos, Vestu\u00e1rio e Cal\u00e7ados":{"P\/VP":3.19,"hoje":28.48,"inicio_ano":28.78,"inicio_mes":25.22,"inicio_seis_meses":21.57,"inicio_semana":28.18,"inicio_tres_meses":25.12,"percent_ano":-1.04,"percent_hoje":1.06,"percent_mes":12.93,"percent_seis_meses":32.04,"percent_semana":1.06,"percent_tres_meses":13.38},"Produtos Diversos":{"P\/VP":8.03,"hoje":30.92,"inicio_ano":19.9,"inicio_mes":30.13,"inicio_seis_meses":31.5,"inicio_semana":32.37,"inicio_tres_meses":46.75,"percent_ano":55.38,"percent_hoje":-4.48,"percent_mes":2.62,"percent_seis_meses":-1.84,"percent_semana":-4.48,"percent_tres_meses":-33.86},"Medicamentos e Outros Produtos":{"P\/VP":4.9,"hoje":21.72,"inicio_ano":66.44,"inicio_mes":19.97,"inicio_seis_meses":19.16,"inicio_semana":21.68,"inicio_tres_meses":23.37,"percent_ano":-67.31,"percent_hoje":0.18,"percent_mes":8.76,"percent_seis_meses":13.36,"percent_semana":0.18,"percent_tres_meses":-7.06},"Servi\u00e7os M\u00e9dico - Hospitalares, An\u00e1lises e Diagn\u00f3sticos":{"P\/VP":5.25,"hoje":33.56,"inicio_ano":18.84,"inicio_mes":32.04,"inicio_seis_meses":30.38,"inicio_semana":33.97,"inicio_tres_meses":34.98,"percent_ano":78.13,"percent_hoje":-1.21,"percent_mes":4.74,"percent_seis_meses":10.47,"percent_semana":-1.21,"percent_tres_meses":-4.06},"Equipamentos":{"P\/VP":1.59,"hoje":16.95,"inicio_ano":11.0,"inicio_mes":16.05,"inicio_seis_meses":11.5,"inicio_semana":16.59,"inicio_tres_meses":17.99,"percent_ano":54.09,"percent_hoje":2.17,"percent_mes":5.61,"percent_seis_meses":47.39,"percent_semana":2.17,"percent_tres_meses":-5.78},"Computadores e Equipamentos":{"P\/VP":0.83,"hoje":4.69,"inicio_ano":2.4,"inicio_mes":3.8,"inicio_seis_meses":4.6,"inicio_semana":4.54,"inicio_tres_meses":5.12,"percent_ano":95.42,"percent_hoje":3.3,"percent_mes":23.42,"percent_seis_meses":1.96,"percent_semana":3.3,"percent_tres_meses":-8.4},"Programas e Servi\u00e7os":{"P\/VP":6.46,"hoje":97.46,"inicio_ano":64.8,"inicio_mes":90.61,"inicio_seis_meses":268.74,"inicio_semana":101.11,"inicio_tres_meses":87.56,"percent_ano":50.4,"percent_hoje":-3.61,"percent_mes":7.56,"percent_seis_meses":-63.73,"percent_semana":-3.61,"percent_tres_meses":11.31},"Telecomunica\u00e7\u00f5es":{"P\/VP":2.68,"hoje":67.9,"inicio_ano":37.72,"inicio_mes":52.05,"inicio_seis_meses":73.83,"inicio_semana":57.09,"inicio_tres_meses":73.14,"percent_ano":80.01,"percent_hoje":18.94,"percent_mes":30.45,"percent_seis_meses":-8.03,"percent_semana":18.94,"percent_tres_meses":-7.16},"Energia El\u00e9trica":{"P\/VP":2.07,"hoje":35.19,"inicio_ano":32.56,"inicio_mes":54.76,"inicio_seis_meses":56.0,"inicio_semana":59.05,"inicio_tres_meses":52.16,"percent_ano":8.08,"percent_hoje":-40.41,"percent_mes":-35.74,"percent_seis_meses":-37.16,"percent_semana":-40.41,"percent_tres_meses":-32.53},"EQTL PARA EQPA":{"P\/VP":334.86,"hoje":18.64,"inicio_ano":12.92,"inicio_mes":17.83,"inicio_seis_meses":15.35,"inicio_semana":18.75,"inicio_tres_meses":19.11,"percent_ano":44.27,"percent_hoje":-0.59,"percent_mes":4.54,"percent_seis_meses":21.43,"percent_semana":-0.59,"percent_tres_meses":-2.46},"\u00c1gua e Saneamento":{"P\/VP":1.29,"hoje":26.01,"inicio_ano":28.85,"inicio_mes":23.95,"inicio_seis_meses":0.43,"inicio_semana":25.91,"inicio_tres_meses":30.74,"percent_ano":-9.84,"percent_hoje":0.39,"percent_mes":8.6,"percent_seis_meses":5948.84,"percent_semana":0.39,"percent_tres_meses":-15.39},"G\u00e1s":{"P\/VP":26.13,"hoje":167.65,"inicio_ano":62.8,"inicio_mes":172.99,"inicio_seis_meses":152.0,"inicio_semana":167.65,"inicio_tres_meses":186.0,"percent_ano":166.96,"percent_hoje":0.0,"percent_mes":-3.09,"percent_seis_meses":10.3,"percent_semana":0.0,"percent_tres_meses":-9.87},"Bancos":{"P\/VP":1.45,"hoje":18.64,"inicio_ano":18.33,"inicio_mes":18.52,"inicio_seis_meses":17.1,"inicio_semana":19.37,"inicio_tres_meses":21.19,"percent_ano":1.69,"percent_hoje":-3.77,"percent_mes":0.65,"percent_seis_meses":9.01,"percent_semana":-3.77,"percent_tres_meses":-12.03},"Soc. Cr\u00e9dito e Financiamento":{"P\/VP":1.04,"hoje":5.5,"inicio_ano":4.69,"inicio_mes":12.2,"inicio_seis_meses":6.14,"inicio_semana":12.3,"inicio_tres_meses":15.19,"percent_ano":17.27,"percent_hoje":-55.28,"percent_mes":-54.92,"percent_seis_meses":-10.42,"percent_semana":-55.28,"percent_tres_meses":-63.79},"Securitizadoras de Receb\u00edveis":{"P\/VP":0.0,"hoje":12.02,"inicio_ano":3.6,"inicio_mes":8.74,"inicio_seis_meses":7.76,"inicio_semana":8.98,"inicio_tres_meses":8.78,"percent_ano":233.89,"percent_hoje":33.85,"percent_mes":37.53,"percent_seis_meses":54.9,"percent_semana":33.85,"percent_tres_meses":36.9},"Gest\u00e3o de Recursos e Investimentos":{"P\/VP":1569.72,"hoje":13.75,"inicio_ano":1.49,"inicio_mes":13.27,"inicio_seis_meses":13.53,"inicio_semana":13.89,"inicio_tres_meses":13.9,"percent_ano":822.82,"percent_hoje":-1.01,"percent_mes":3.62,"percent_seis_meses":1.63,"percent_semana":-1.01,"percent_tres_meses":-1.08},"Servi\u00e7os Financeiros Diversos":{"P\/VP":3.19,"hoje":28.92,"inicio_ano":18.71,"inicio_mes":27.14,"inicio_seis_meses":21.24,"inicio_semana":29.12,"inicio_tres_meses":34.64,"percent_ano":54.57,"percent_hoje":-0.69,"percent_mes":6.56,"percent_seis_meses":36.16,"percent_semana":-0.69,"percent_tres_meses":-16.51},"Seguradoras":{"P\/VP":3.59,"hoje":25.69,"inicio_ano":24.9,"inicio_mes":20.94,"inicio_seis_meses":22.03,"inicio_semana":22.3,"inicio_tres_meses":25.13,"percent_ano":3.17,"percent_hoje":15.2,"percent_mes":22.68,"percent_seis_meses":16.61,"percent_semana":15.2,"percent_tres_meses":2.23},"Corretoras de Seguros":{"P\/VP":4.1,"hoje":21.05,"inicio_ano":12.21,"inicio_mes":18.79,"inicio_seis_meses":13.56,"inicio_semana":21.18,"inicio_tres_meses":19.5,"percent_ano":72.4,"percent_hoje":-0.61,"percent_mes":12.03,"percent_seis_meses":55.24,"percent_semana":-0.61,"percent_tres_meses":7.95},"Explora\u00e7\u00e3o de Im\u00f3veis":{"P\/VP":1.32,"hoje":25.2,"inicio_ano":36.92,"inicio_mes":22.02,"inicio_seis_meses":21.66,"inicio_semana":25.18,"inicio_tres_meses":24.18,"percent_ano":-31.74,"percent_hoje":0.08,"percent_mes":14.44,"percent_seis_meses":16.34,"percent_semana":0.08,"percent_tres_meses":4.22},"Intermedia\u00e7\u00e3o Imobili\u00e1ria":{"P\/VP":2.58,"hoje":3.32,"inicio_ano":6.56,"inicio_mes":3.13,"inicio_seis_meses":3.15,"inicio_semana":3.35,"inicio_tres_meses":3.4,"percent_ano":-49.39,"percent_hoje":-0.9,"percent_mes":6.07,"percent_seis_meses":5.4,"percent_semana":-0.9,"percent_tres_meses":-2.35},"Holdings Diversificadas":{"P\/VP":2.0,"hoje":207.88,"inicio_ano":86.86,"inicio_mes":207.99,"inicio_seis_meses":71.5,"inicio_semana":207.88,"inicio_tres_meses":99.05,"percent_ano":139.33,"percent_hoje":0.0,"percent_mes":-0.05,"percent_seis_meses":190.74,"percent_semana":0.0,"percent_tres_meses":109.87},"Outros":{"P\/VP":2.62,"hoje":9.01,"inicio_ano":10.25,"inicio_mes":8.7,"inicio_seis_meses":12.03,"inicio_semana":8.89,"inicio_tres_meses":8.56,"percent_ano":-12.1,"percent_hoje":1.35,"percent_mes":3.56,"percent_seis_meses":-25.1,"percent_semana":1.35,"percent_tres_meses":5.26},"^BVSP":{"P\/VP":0.0,"hoje":105066.96,"inicio_ano":91012.0,"inicio_mes":95587.0,"inicio_seis_meses":80506.0,"inicio_semana":103913.0,"inicio_tres_meses":102830.0,"percent_ano":15.44,"percent_hoje":1.11,"percent_mes":9.92,"percent_seis_meses":30.51,"percent_semana":1.11,"percent_tres_meses":2.18}}