{"Explora\u00e7\u00e3o, Refino e Distribui\u00e7\u00e3o":{"P\/VP":2.15,"hoje":26.51,"inicio_ano":18.67,"inicio_mes":20.88,"inicio_seis_meses":18.38,"inicio_semana":26.51,"inicio_tres_meses":25.72,"percent_ano":41.99,"percent_hoje":2.24,"percent_mes":26.96,"percent_seis_meses":44.23,"percent_semana":0.0,"percent_tres_meses":3.07},"Equipamentos e Servi\u00e7os":{"P\/VP":0.75,"hoje":6.38,"inicio_ano":2.67,"inicio_mes":6.53,"inicio_seis_meses":2.31,"inicio_semana":6.38,"inicio_tres_meses":3.4,"percent_ano":138.95,"percent_hoje":-3.04,"percent_mes":-2.3,"percent_seis_meses":176.19,"percent_semana":0.0,"percent_tres_meses":87.65},"Minerais Met\u00e1licos":{"P\/VP":1.52,"hoje":43.34,"inicio_ano":27.3,"inicio_mes":39.23,"inicio_seis_meses":24.33,"inicio_semana":43.34,"inicio_tres_meses":33.53,"percent_ano":58.75,"percent_hoje":3.91,"percent_mes":10.48,"percent_seis_meses":78.13,"percent_semana":0.0,"percent_tres_meses":29.26},"Siderurgia":{"P\/VP":1.68,"hoje":15.59,"inicio_ano":12.33,"inicio_mes":16.21,"inicio_seis_meses":9.34,"inicio_semana":15.59,"inicio_tres_meses":12.44,"percent_ano":26.44,"percent_hoje":3.11,"percent_mes":-3.82,"percent_seis_meses":66.92,"percent_semana":0.0,"percent_tres_meses":25.32},"Artefatos de Ferro e A\u00e7o":{"P\/VP":0.72,"hoje":5.42,"inicio_ano":9.68,"inicio_mes":15.36,"inicio_seis_meses":13.36,"inicio_semana":5.42,"inicio_tres_meses":17.04,"percent_ano":-44.01,"percent_hoje":-0.55,"percent_mes":-64.71,"percent_seis_meses":-59.43,"percent_semana":0.0,"percent_tres_meses":-68.19},"Artefatos de Cobre":{"P\/VP":0.0,"hoje":10.61,"inicio_ano":23.97,"inicio_mes":9.62,"inicio_seis_meses":11.07,"inicio_semana":10.61,"inicio_tres_meses":12.25,"percent_ano":-55.74,"percent_hoje":-0.84,"percent_mes":10.29,"percent_seis_meses":-4.16,"percent_semana":0.0,"percent_tres_meses":-13.39},"Petroqu\u00edmicos":{"P\/VP":0.61,"hoje":20.37,"inicio_ano":19.88,"inicio_mes":19.72,"inicio_seis_meses":15.22,"inicio_semana":20.37,"inicio_tres_meses":16.86,"percent_ano":2.46,"percent_hoje":0.15,"percent_mes":3.3,"percent_seis_meses":33.84,"percent_semana":0.0,"percent_tres_meses":20.82},"Fertilizantes e Defensivos":{"P\/VP":0.62,"hoje":2.7,"inicio_ano":17.33,"inicio_mes":2.85,"inicio_seis_meses":30.18,"inicio_semana":2.7,"inicio_tres_meses":45.48,"percent_ano":-84.42,"percent_hoje":-6.9,"percent_mes":-5.26,"percent_seis_meses":-91.05,"percent_semana":0.0,"percent_tres_meses":-94.06},"Qu\u00edmicos Diversos":{"P\/VP":1.76,"hoje":37.9,"inicio_ano":29.51,"inicio_mes":31.25,"inicio_seis_meses":25.62,"inicio_semana":37.9,"inicio_tres_meses":27.68,"percent_ano":28.43,"percent_hoje":1.07,"percent_mes":21.28,"percent_seis_meses":47.93,"percent_semana":0.0,"percent_tres_meses":36.92},"Madeira":{"P\/VP":1.96,"hoje":21.36,"inicio_ano":10.81,"inicio_mes":21.1,"inicio_seis_meses":12.17,"inicio_semana":21.36,"inicio_tres_meses":20.13,"percent_ano":97.59,"percent_hoje":-1.07,"percent_mes":1.23,"percent_seis_meses":75.51,"percent_semana":0.0,"percent_tres_meses":6.11},"Papel e Celulose":{"P\/VP":10.8,"hoje":20.18,"inicio_ano":23.53,"inicio_mes":27.52,"inicio_seis_meses":15.4,"inicio_semana":20.18,"inicio_tres_meses":17.13,"percent_ano":-14.24,"percent_hoje":-1.18,"percent_mes":-26.67,"percent_seis_meses":31.04,"percent_semana":0.0,"percent_tres_meses":17.81},"Embalagens":{"P\/VP":0.29,"hoje":42.5,"inicio_ano":93.0,"inicio_mes":38.01,"inicio_seis_meses":50.0,"inicio_semana":42.5,"inicio_tres_meses":38.06,"percent_ano":-54.3,"percent_hoje":-5.56,"percent_mes":11.81,"percent_seis_meses":-15.0,"percent_semana":0.0,"percent_tres_meses":11.67},"Materiais Diversos":{"P\/VP":0.0,"hoje":31.5,"inicio_ano":1.12,"inicio_mes":32.2,"inicio_seis_meses":1.12,"inicio_semana":31.5,"inicio_tres_meses":1.12,"percent_ano":2712.5,"percent_hoje":0.0,"percent_mes":-2.17,"percent_seis_meses":2712.5,"percent_semana":0.0,"percent_tres_meses":2712.5},"Produtos para Constru\u00e7\u00e3o":{"P\/VP":3.72,"hoje":7.78,"inicio_ano":3.74,"inicio_mes":6.84,"inicio_seis_meses":2.73,"inicio_semana":7.78,"inicio_tres_meses":4.27,"percent_ano":108.02,"percent_hoje":6.58,"percent_mes":13.74,"percent_seis_meses":184.98,"percent_semana":0.0,"percent_tres_meses":82.2},"Constru\u00e7\u00e3o Pesada":{"P\/VP":0.0,"hoje":9.59,"inicio_ano":45.0,"inicio_mes":12.15,"inicio_seis_meses":3.78,"inicio_semana":9.59,"inicio_tres_meses":12.2,"percent_ano":-78.69,"percent_hoje":-3.62,"percent_mes":-21.07,"percent_seis_meses":153.7,"percent_semana":0.0,"percent_tres_meses":-21.39},"Engenharia Consultiva":{"P\/VP":27.76,"hoje":22.68,"inicio_ano":8.8,"inicio_mes":21.75,"inicio_seis_meses":1.55,"inicio_semana":22.68,"inicio_tres_meses":19.08,"percent_ano":157.73,"percent_hoje":-0.22,"percent_mes":4.28,"percent_seis_meses":1363.23,"percent_semana":0.0,"percent_tres_meses":18.87},"Servi\u00e7os Diversos":{"P\/VP":6.52,"hoje":8.48,"inicio_ano":11.77,"inicio_mes":8.0,"inicio_seis_meses":7.17,"inicio_semana":8.48,"inicio_tres_meses":8.96,"percent_ano":-27.95,"percent_hoje":0.24,"percent_mes":6.0,"percent_seis_meses":18.27,"percent_semana":0.0,"percent_tres_meses":-5.36},"Material Aeron\u00e1utico e de Defesa":{"P\/VP":0.34,"hoje":8.21,"inicio_ano":21.54,"inicio_mes":6.03,"inicio_seis_meses":8.65,"inicio_semana":8.21,"inicio_tres_meses":7.66,"percent_ano":-61.88,"percent_hoje":2.24,"percent_mes":36.15,"percent_seis_meses":-5.09,"percent_semana":0.0,"percent_tres_meses":7.18},"Material Rodovi\u00e1rio":{"P\/VP":3.38,"hoje":9.24,"inicio_ano":15.27,"inicio_mes":43.02,"inicio_seis_meses":20.21,"inicio_semana":9.24,"inicio_tres_meses":34.42,"percent_ano":-39.49,"percent_hoje":0.33,"percent_mes":-78.52,"percent_seis_meses":-54.28,"percent_semana":0.0,"percent_tres_meses":-73.16},"Motores, Compressores e Outros":{"P\/VP":7.67,"hoje":45.36,"inicio_ano":12.54,"inicio_mes":44.9,"inicio_seis_meses":24.12,"inicio_semana":45.36,"inicio_tres_meses":39.11,"percent_ano":261.72,"percent_hoje":-1.99,"percent_mes":1.02,"percent_seis_meses":88.06,"percent_semana":0.0,"percent_tres_meses":15.98},"M\u00e1q. e Equip. Industriais":{"P\/VP":-4.46,"hoje":15.02,"inicio_ano":15.72,"inicio_mes":14.05,"inicio_seis_meses":10.74,"inicio_semana":15.02,"inicio_tres_meses":25.85,"percent_ano":-4.45,"percent_hoje":-0.13,"percent_mes":6.9,"percent_seis_meses":39.85,"percent_semana":0.0,"percent_tres_meses":-41.9},"M\u00e1q. e Equip. Constru\u00e7\u00e3o e Agr\u00edcolas":{"P\/VP":0.76,"hoje":30.55,"inicio_ano":15.05,"inicio_mes":26.5,"inicio_seis_meses":16.1,"inicio_semana":30.55,"inicio_tres_meses":22.4,"percent_ano":102.99,"percent_hoje":-4.47,"percent_mes":15.28,"percent_seis_meses":89.75,"percent_semana":0.0,"percent_tres_meses":36.38},"Armas e Muni\u00e7\u00f5es":{"P\/VP":0.0,"hoje":9.67,"inicio_ano":7.21,"inicio_mes":7.33,"inicio_seis_meses":3.5,"inicio_semana":9.67,"inicio_tres_meses":5.1,"percent_ano":34.12,"percent_hoje":-0.82,"percent_mes":31.92,"percent_seis_meses":176.29,"percent_semana":0.0,"percent_tres_meses":89.61},"Transporte A\u00e9reo":{"P\/VP":0.0,"hoje":29.16,"inicio_ano":30.89,"inicio_mes":19.05,"inicio_seis_meses":14.9,"inicio_semana":29.16,"inicio_tres_meses":18.86,"percent_ano":-5.6,"percent_hoje":-0.51,"percent_mes":53.07,"percent_seis_meses":95.7,"percent_semana":0.0,"percent_tres_meses":54.61},"Transporte Ferrovi\u00e1rio":{"P\/VP":4.07,"hoje":18.21,"inicio_ano":15.06,"inicio_mes":17.35,"inicio_seis_meses":17.58,"inicio_semana":18.21,"inicio_tres_meses":21.06,"percent_ano":20.92,"percent_hoje":2.48,"percent_mes":4.96,"percent_seis_meses":3.58,"percent_semana":0.0,"percent_tres_meses":-13.53},"Transporte Hidrovi\u00e1rio":{"P\/VP":5.5,"hoje":38.22,"inicio_ano":13.07,"inicio_mes":37.5,"inicio_seis_meses":21.88,"inicio_semana":38.22,"inicio_tres_meses":30.22,"percent_ano":192.43,"percent_hoje":-1.04,"percent_mes":1.92,"percent_seis_meses":74.68,"percent_semana":0.0,"percent_tres_meses":26.47},"Transporte Rodovi\u00e1rio":{"P\/VP":3.79,"hoje":18.33,"inicio_ano":17.74,"inicio_mes":21.12,"inicio_seis_meses":18.8,"inicio_semana":18.33,"inicio_tres_meses":27.81,"percent_ano":3.33,"percent_hoje":2.8,"percent_mes":-13.21,"percent_seis_meses":-2.5,"percent_semana":0.0,"percent_tres_meses":-34.09},"Explora\u00e7\u00e3o de Rodovias":{"P\/VP":5.27,"hoje":8.47,"inicio_ano":7.77,"inicio_mes":7.49,"inicio_seis_meses":7.94,"inicio_semana":8.47,"inicio_tres_meses":10.02,"percent_ano":9.01,"percent_hoje":-1.51,"percent_mes":13.08,"percent_seis_meses":6.68,"percent_semana":0.0,"percent_tres_meses":-15.47},"Servi\u00e7os de Apoio e Armazenagem":{"P\/VP":2.78,"hoje":4.01,"inicio_ano":29.62,"inicio_mes":3.46,"inicio_seis_meses":3.23,"inicio_semana":4.01,"inicio_tres_meses":4.65,"percent_ano":-86.46,"percent_hoje":1.52,"percent_mes":15.9,"percent_seis_meses":24.15,"percent_semana":0.0,"percent_tres_meses":-13.76},"Material de Transporte":{"P\/VP":6.89,"hoje":13.95,"inicio_ano":4.28,"inicio_mes":10.4,"inicio_seis_meses":8.35,"inicio_semana":13.95,"inicio_tres_meses":12.7,"percent_ano":225.93,"percent_hoje":0.0,"percent_mes":34.13,"percent_seis_meses":67.07,"percent_semana":0.0,"percent_tres_meses":9.84},"Agricultura":{"P\/VP":1.06,"hoje":19.03,"inicio_ano":18.87,"inicio_mes":17.13,"inicio_seis_meses":15.03,"inicio_semana":19.03,"inicio_tres_meses":16.71,"percent_ano":0.85,"percent_hoje":1.28,"percent_mes":11.09,"percent_seis_meses":26.61,"percent_semana":0.0,"percent_tres_meses":13.88},"A\u00e7ucar e Alcool":{"P\/VP":-0.87,"hoje":15.19,"inicio_ano":10.79,"inicio_mes":12.83,"inicio_seis_meses":10.95,"inicio_semana":15.19,"inicio_tres_meses":12.28,"percent_ano":40.78,"percent_hoje":2.36,"percent_mes":18.39,"percent_seis_meses":38.72,"percent_semana":0.0,"percent_tres_meses":23.7},"Carnes e Derivados":{"P\/VP":10.39,"hoje":26.88,"inicio_ano":11.05,"inicio_mes":24.76,"inicio_seis_meses":27.18,"inicio_semana":26.88,"inicio_tres_meses":28.07,"percent_ano":143.26,"percent_hoje":1.47,"percent_mes":8.56,"percent_seis_meses":-1.1,"percent_semana":0.0,"percent_tres_meses":-4.24},"Alimentos Diversos":{"P\/VP":2.05,"hoje":22.29,"inicio_ano":26.13,"inicio_mes":22.33,"inicio_seis_meses":20.08,"inicio_semana":22.29,"inicio_tres_meses":25.17,"percent_ano":-14.7,"percent_hoje":0.09,"percent_mes":-0.18,"percent_seis_meses":11.01,"percent_semana":0.0,"percent_tres_meses":-11.44},"Cervejas e Refrigerantes":{"P\/VP":2.76,"hoje":14.66,"inicio_ano":16.15,"inicio_mes":12.78,"inicio_seis_meses":11.34,"inicio_semana":14.66,"inicio_tres_meses":13.71,"percent_ano":-9.23,"percent_hoje":0.69,"percent_mes":14.71,"percent_seis_meses":29.28,"percent_semana":0.0,"percent_tres_meses":6.93},"Produtos de Uso Pessoal":{"P\/VP":2.68,"hoje":48.21,"inicio_ano":null,"inicio_mes":46.43,"inicio_seis_meses":35.52,"inicio_semana":48.21,"inicio_tres_meses":46.61,"percent_ano":null,"percent_hoje":-1.11,"percent_mes":3.83,"percent_seis_meses":35.73,"percent_semana":0.0,"percent_tres_meses":3.43},"Produtos de Limpeza":{"P\/VP":0.0,"hoje":2.0,"inicio_ano":2.74,"inicio_mes":1.81,"inicio_seis_meses":1.72,"inicio_semana":2.0,"inicio_tres_meses":2.18,"percent_ano":-27.01,"percent_hoje":-0.5,"percent_mes":10.5,"percent_seis_meses":16.28,"percent_semana":0.0,"percent_tres_meses":-8.26},"Alimentos":{"P\/VP":2.01,"hoje":44.7,"inicio_ano":51.98,"inicio_mes":40.47,"inicio_seis_meses":43.11,"inicio_semana":44.7,"inicio_tres_meses":45.4,"percent_ano":-14.01,"percent_hoje":-3.79,"percent_mes":10.45,"percent_seis_meses":3.69,"percent_semana":0.0,"percent_tres_meses":-1.54},"Incorpora\u00e7\u00f5es":{"P\/VP":1.54,"hoje":13.32,"inicio_ano":8.65,"inicio_mes":11.21,"inicio_seis_meses":0.02,"inicio_semana":13.32,"inicio_tres_meses":13.95,"percent_ano":53.99,"percent_hoje":-1.04,"percent_mes":18.82,"percent_seis_meses":66500.0,"percent_semana":0.0,"percent_tres_meses":-4.52},"Fios e Tecidos":{"P\/VP":0.76,"hoje":8.83,"inicio_ano":6.08,"inicio_mes":13.95,"inicio_seis_meses":7.02,"inicio_semana":8.83,"inicio_tres_meses":33.82,"percent_ano":45.23,"percent_hoje":0.34,"percent_mes":-36.7,"percent_seis_meses":25.78,"percent_semana":0.0,"percent_tres_meses":-73.89},"Vestu\u00e1rio":{"P\/VP":1.9,"hoje":17.09,"inicio_ano":30.21,"inicio_mes":16.32,"inicio_seis_meses":14.96,"inicio_semana":17.09,"inicio_tres_meses":14.37,"percent_ano":-43.43,"percent_hoje":-1.73,"percent_mes":4.72,"percent_seis_meses":14.24,"percent_semana":0.0,"percent_tres_meses":18.93},"Cal\u00e7ados":{"P\/VP":3.2,"hoje":14.23,"inicio_ano":9.69,"inicio_mes":13.67,"inicio_seis_meses":9.04,"inicio_semana":14.23,"inicio_tres_meses":11.14,"percent_ano":46.85,"percent_hoje":1.64,"percent_mes":4.1,"percent_seis_meses":57.41,"percent_semana":0.0,"percent_tres_meses":27.74},"Acess\u00f3rios":{"P\/VP":2.27,"hoje":16.51,"inicio_ano":14.81,"inicio_mes":14.31,"inicio_seis_meses":9.89,"inicio_semana":16.51,"inicio_tres_meses":15.88,"percent_ano":11.48,"percent_hoje":-2.94,"percent_mes":15.37,"percent_seis_meses":66.94,"percent_semana":0.0,"percent_tres_meses":3.97},"Eletrodom\u00e9sticos":{"P\/VP":10.35,"hoje":16.11,"inicio_ano":4.8,"inicio_mes":16.32,"inicio_seis_meses":9.44,"inicio_semana":16.11,"inicio_tres_meses":16.05,"percent_ano":235.62,"percent_hoje":-2.3,"percent_mes":-1.29,"percent_seis_meses":70.66,"percent_semana":0.0,"percent_tres_meses":0.37},"Utens\u00edlios Dom\u00e9sticos":{"P\/VP":0.0,"hoje":7.55,"inicio_ano":6.82,"inicio_mes":7.4,"inicio_seis_meses":4.6,"inicio_semana":7.55,"inicio_tres_meses":8.0,"percent_ano":10.7,"percent_hoje":2.86,"percent_mes":2.03,"percent_seis_meses":64.13,"percent_semana":0.0,"percent_tres_meses":-5.63},"Autom\u00f3veis e Motocicletas":{"P\/VP":0.92,"hoje":12.48,"inicio_ano":19.75,"inicio_mes":12.24,"inicio_seis_meses":11.6,"inicio_semana":12.48,"inicio_tres_meses":11.71,"percent_ano":-36.81,"percent_hoje":-0.79,"percent_mes":1.96,"percent_seis_meses":7.59,"percent_semana":0.0,"percent_tres_meses":6.58},"Hotelaria":{"P\/VP":0.0,"hoje":2.84,"inicio_ano":1.91,"inicio_mes":2.66,"inicio_seis_meses":1.96,"inicio_semana":2.84,"inicio_tres_meses":2.68,"percent_ano":48.69,"percent_hoje":1.07,"percent_mes":6.77,"percent_seis_meses":44.9,"percent_semana":0.0,"percent_tres_meses":5.97},"Restaurante e Similares":{"P\/VP":1.25,"hoje":7.23,"inicio_ano":13.8,"inicio_mes":6.22,"inicio_seis_meses":6.36,"inicio_semana":7.23,"inicio_tres_meses":7.19,"percent_ano":-47.61,"percent_hoje":-0.14,"percent_mes":16.24,"percent_seis_meses":13.68,"percent_semana":0.0,"percent_tres_meses":0.56},"Bicicletas":{"P\/VP":0.52,"hoje":237.0,"inicio_ano":282.5,"inicio_mes":238.5,"inicio_seis_meses":187.0,"inicio_semana":237.0,"inicio_tres_meses":216.0,"percent_ano":-16.11,"percent_hoje":-0.84,"percent_mes":-0.63,"percent_seis_meses":26.74,"percent_semana":0.0,"percent_tres_meses":9.72},"Brinquedos e Jogos":{"P\/VP":0.0,"hoje":25.29,"inicio_ano":12.5,"inicio_mes":25.0,"inicio_seis_meses":38.98,"inicio_semana":25.29,"inicio_tres_meses":29.3,"percent_ano":102.32,"percent_hoje":0.0,"percent_mes":1.16,"percent_seis_meses":-35.12,"percent_semana":0.0,"percent_tres_meses":-13.69},"Produ\u00e7\u00e3o de Eventos e Shows":{"P\/VP":4.96,"hoje":13.4,"inicio_ano":40.93,"inicio_mes":2.25,"inicio_seis_meses":1.87,"inicio_semana":13.4,"inicio_tres_meses":13.83,"percent_ano":-67.26,"percent_hoje":-3.67,"percent_mes":495.56,"percent_seis_meses":616.58,"percent_semana":0.0,"percent_tres_meses":-3.11},"Viagens e Turismo":{"P\/VP":3.58,"hoje":16.33,"inicio_ano":61.1,"inicio_mes":11.88,"inicio_seis_meses":13.8,"inicio_semana":16.33,"inicio_tres_meses":20.0,"percent_ano":-73.27,"percent_hoje":-0.43,"percent_mes":37.46,"percent_seis_meses":18.33,"percent_semana":0.0,"percent_tres_meses":-18.35},"Servi\u00e7os Educacionais":{"P\/VP":1.97,"hoje":30.74,"inicio_ano":36.68,"inicio_mes":30.91,"inicio_seis_meses":29.13,"inicio_semana":30.74,"inicio_tres_meses":44.71,"percent_ano":-16.19,"percent_hoje":0.03,"percent_mes":-0.55,"percent_seis_meses":5.53,"percent_semana":0.0,"percent_tres_meses":-31.25},"Aluguel de carros":{"P\/VP":3.88,"hoje":37.1,"inicio_ano":17.09,"inicio_mes":36.14,"inicio_seis_meses":19.42,"inicio_semana":37.1,"inicio_tres_meses":28.58,"percent_ano":117.09,"percent_hoje":-0.48,"percent_mes":2.66,"percent_seis_meses":91.04,"percent_semana":0.0,"percent_tres_meses":29.81},"Programas de Fideliza\u00e7\u00e3o":{"P\/VP":1.37,"hoje":19.4,"inicio_ano":43.5,"inicio_mes":14.12,"inicio_seis_meses":14.28,"inicio_semana":19.4,"inicio_tres_meses":15.0,"percent_ano":-55.4,"percent_hoje":0.47,"percent_mes":37.39,"percent_seis_meses":35.85,"percent_semana":0.0,"percent_tres_meses":29.33},"Tecidos, Vestu\u00e1rio e Cal\u00e7ados":{"P\/VP":3.19,"hoje":29.46,"inicio_ano":28.78,"inicio_mes":25.22,"inicio_seis_meses":21.57,"inicio_semana":29.46,"inicio_tres_meses":25.12,"percent_ano":2.36,"percent_hoje":0.03,"percent_mes":16.81,"percent_seis_meses":36.58,"percent_semana":0.0,"percent_tres_meses":17.28},"Produtos Diversos":{"P\/VP":8.03,"hoje":30.53,"inicio_ano":19.9,"inicio_mes":30.13,"inicio_seis_meses":31.5,"inicio_semana":30.53,"inicio_tres_meses":46.75,"percent_ano":53.42,"percent_hoje":-2.86,"percent_mes":1.33,"percent_seis_meses":-3.08,"percent_semana":0.0,"percent_tres_meses":-34.7},"Medicamentos e Outros Produtos":{"P\/VP":4.9,"hoje":21.95,"inicio_ano":66.44,"inicio_mes":19.97,"inicio_seis_meses":19.16,"inicio_semana":21.95,"inicio_tres_meses":23.37,"percent_ano":-66.96,"percent_hoje":-2.05,"percent_mes":9.91,"percent_seis_meses":14.56,"percent_semana":0.0,"percent_tres_meses":-6.08},"Servi\u00e7os M\u00e9dico - Hospitalares, An\u00e1lises e Diagn\u00f3sticos":{"P\/VP":5.25,"hoje":31.78,"inicio_ano":18.84,"inicio_mes":32.04,"inicio_seis_meses":25.42,"inicio_semana":31.78,"inicio_tres_meses":30.48,"percent_ano":68.68,"percent_hoje":0.6,"percent_mes":-0.81,"percent_seis_meses":25.02,"percent_semana":0.0,"percent_tres_meses":4.27},"Equipamentos":{"P\/VP":1.59,"hoje":15.8,"inicio_ano":11.0,"inicio_mes":16.05,"inicio_seis_meses":11.5,"inicio_semana":15.8,"inicio_tres_meses":17.99,"percent_ano":43.64,"percent_hoje":3.61,"percent_mes":-1.56,"percent_seis_meses":37.39,"percent_semana":0.0,"percent_tres_meses":-12.17},"Computadores e Equipamentos":{"P\/VP":0.83,"hoje":4.74,"inicio_ano":2.4,"inicio_mes":3.8,"inicio_seis_meses":4.6,"inicio_semana":4.74,"inicio_tres_meses":5.12,"percent_ano":97.5,"percent_hoje":-3.27,"percent_mes":24.74,"percent_seis_meses":3.04,"percent_semana":0.0,"percent_tres_meses":-7.42},"Programas e Servi\u00e7os":{"P\/VP":6.46,"hoje":96.18,"inicio_ano":64.8,"inicio_mes":90.61,"inicio_seis_meses":268.74,"inicio_semana":96.18,"inicio_tres_meses":87.56,"percent_ano":48.43,"percent_hoje":0.6,"percent_mes":6.15,"percent_seis_meses":-64.21,"percent_semana":0.0,"percent_tres_meses":9.84},"Telecomunica\u00e7\u00f5es":{"P\/VP":2.68,"hoje":81.55,"inicio_ano":37.72,"inicio_mes":52.05,"inicio_seis_meses":73.83,"inicio_semana":81.55,"inicio_tres_meses":73.14,"percent_ano":116.2,"percent_hoje":16.57,"percent_mes":56.68,"percent_seis_meses":10.46,"percent_semana":0.0,"percent_tres_meses":11.5},"Energia El\u00e9trica":{"P\/VP":2.07,"hoje":38.27,"inicio_ano":32.56,"inicio_mes":31.07,"inicio_seis_meses":29.17,"inicio_semana":38.27,"inicio_tres_meses":30.47,"percent_ano":17.54,"percent_hoje":0.05,"percent_mes":23.17,"percent_seis_meses":31.2,"percent_semana":0.0,"percent_tres_meses":25.6},"EQTL PARA EQPA":{"P\/VP":334.86,"hoje":19.58,"inicio_ano":12.92,"inicio_mes":17.83,"inicio_seis_meses":15.35,"inicio_semana":19.58,"inicio_tres_meses":19.11,"percent_ano":51.55,"percent_hoje":-0.96,"percent_mes":9.81,"percent_seis_meses":27.56,"percent_semana":0.0,"percent_tres_meses":2.46},"\u00c1gua e Saneamento":{"P\/VP":1.29,"hoje":24.13,"inicio_ano":28.85,"inicio_mes":23.95,"inicio_seis_meses":31.07,"inicio_semana":24.13,"inicio_tres_meses":30.74,"percent_ano":-16.36,"percent_hoje":0.96,"percent_mes":0.75,"percent_seis_meses":-22.34,"percent_semana":0.0,"percent_tres_meses":-21.5},"G\u00e1s":{"P\/VP":26.13,"hoje":171.0,"inicio_ano":62.8,"inicio_mes":172.99,"inicio_seis_meses":152.0,"inicio_semana":171.0,"inicio_tres_meses":186.0,"percent_ano":172.29,"percent_hoje":-0.03,"percent_mes":-1.15,"percent_seis_meses":12.5,"percent_semana":0.0,"percent_tres_meses":-8.06},"Bancos":{"P\/VP":1.45,"hoje":19.5,"inicio_ano":18.33,"inicio_mes":17.72,"inicio_seis_meses":16.28,"inicio_semana":19.5,"inicio_tres_meses":20.15,"percent_ano":6.38,"percent_hoje":-0.41,"percent_mes":10.05,"percent_seis_meses":19.78,"percent_semana":0.0,"percent_tres_meses":-3.23},"Soc. Cr\u00e9dito e Financiamento":{"P\/VP":1.04,"hoje":5.51,"inicio_ano":4.69,"inicio_mes":5.41,"inicio_seis_meses":5.19,"inicio_semana":5.51,"inicio_tres_meses":5.38,"percent_ano":17.48,"percent_hoje":0.18,"percent_mes":1.85,"percent_seis_meses":6.17,"percent_semana":0.0,"percent_tres_meses":2.42},"Securitizadoras de Receb\u00edveis":{"P\/VP":0.0,"hoje":11.77,"inicio_ano":3.6,"inicio_mes":11.65,"inicio_seis_meses":15.34,"inicio_semana":11.77,"inicio_tres_meses":16.73,"percent_ano":226.94,"percent_hoje":-0.68,"percent_mes":1.03,"percent_seis_meses":-23.27,"percent_semana":0.0,"percent_tres_meses":-29.65},"Gest\u00e3o de Recursos e Investimentos":{"P\/VP":1569.72,"hoje":11.74,"inicio_ano":1.49,"inicio_mes":13.27,"inicio_seis_meses":13.53,"inicio_semana":11.74,"inicio_tres_meses":13.9,"percent_ano":687.92,"percent_hoje":1.65,"percent_mes":-11.53,"percent_seis_meses":-13.23,"percent_semana":0.0,"percent_tres_meses":-15.54},"Servi\u00e7os Financeiros Diversos":{"P\/VP":3.19,"hoje":28.93,"inicio_ano":18.71,"inicio_mes":27.14,"inicio_seis_meses":21.24,"inicio_semana":28.93,"inicio_tres_meses":34.64,"percent_ano":54.62,"percent_hoje":-1.2,"percent_mes":6.6,"percent_seis_meses":36.21,"percent_semana":0.0,"percent_tres_meses":-16.48},"Seguradoras":{"P\/VP":3.59,"hoje":22.91,"inicio_ano":24.9,"inicio_mes":23.69,"inicio_seis_meses":25.54,"inicio_semana":22.91,"inicio_tres_meses":27.56,"percent_ano":-7.99,"percent_hoje":0.17,"percent_mes":-3.29,"percent_seis_meses":-10.3,"percent_semana":0.0,"percent_tres_meses":-16.87},"Corretoras de Seguros":{"P\/VP":4.1,"hoje":21.47,"inicio_ano":12.21,"inicio_mes":18.79,"inicio_seis_meses":13.56,"inicio_semana":21.47,"inicio_tres_meses":19.5,"percent_ano":75.84,"percent_hoje":0.47,"percent_mes":14.26,"percent_seis_meses":58.33,"percent_semana":0.0,"percent_tres_meses":10.1},"Explora\u00e7\u00e3o de Im\u00f3veis":{"P\/VP":1.32,"hoje":24.46,"inicio_ano":36.92,"inicio_mes":22.02,"inicio_seis_meses":19.83,"inicio_semana":24.46,"inicio_tres_meses":24.18,"percent_ano":-33.75,"percent_hoje":-0.08,"percent_mes":11.08,"percent_seis_meses":23.35,"percent_semana":0.0,"percent_tres_meses":1.16},"Intermedia\u00e7\u00e3o Imobili\u00e1ria":{"P\/VP":2.58,"hoje":3.25,"inicio_ano":6.56,"inicio_mes":3.13,"inicio_seis_meses":3.15,"inicio_semana":3.25,"inicio_tres_meses":3.4,"percent_ano":-50.46,"percent_hoje":0.93,"percent_mes":3.83,"percent_seis_meses":3.17,"percent_semana":0.0,"percent_tres_meses":-4.41},"Holdings Diversificadas":{"P\/VP":2.0,"hoje":215.0,"inicio_ano":86.86,"inicio_mes":207.99,"inicio_seis_meses":71.5,"inicio_semana":215.0,"inicio_tres_meses":99.05,"percent_ano":147.52,"percent_hoje":-0.46,"percent_mes":3.37,"percent_seis_meses":200.7,"percent_semana":0.0,"percent_tres_meses":117.06},"Outros":{"P\/VP":2.62,"hoje":8.85,"inicio_ano":10.25,"inicio_mes":8.7,"inicio_seis_meses":12.03,"inicio_semana":8.85,"inicio_tres_meses":8.56,"percent_ano":-13.66,"percent_hoje":-0.67,"percent_mes":1.72,"percent_seis_meses":-26.43,"percent_semana":0.0,"percent_tres_meses":3.39},"^BVSP":{"P\/VP":0.0,"hoje":107378.92,"inicio_ano":91012.0,"inicio_mes":95587.0,"inicio_seis_meses":80506.0,"inicio_semana":107378.92,"inicio_tres_meses":102830.0,"percent_ano":17.98,"percent_hoje":1.25,"percent_mes":12.34,"percent_seis_meses":33.38,"percent_semana":0.0,"percent_tres_meses":4.42}}